tidyarxiv/__init__.py
tidyarxiv/tidyarxiv.py
tidyarxiv-1.0.1.dist-info/METADATA
tidyarxiv-1.0.1.dist-info/WHEEL
tidyarxiv-1.0.1.dist-info/entry_points.txt
tidyarxiv-1.0.1.dist-info/RECORD
