Metadata-Version: 2.1
Name: tidyarxiv
Version: 1.0.1
Summary: A simple script to prepare your LaTeX paper for arXiv submission
License: GPL-3.0-only
Author: Dionysis Zindros
Author-email: dionyziz@stanford.edu
Requires-Python: >=3.10,<4.0
Classifier: License :: OSI Approved :: GNU General Public License v3 (GPLv3)
Classifier: Programming Language :: Python :: 3
Classifier: Programming Language :: Python :: 3.10
Classifier: Programming Language :: Python :: 3.11
